datasette_statistics/__init__.py
datasette_statistics-0.2.1.dist-info/METADATA
datasette_statistics-0.2.1.dist-info/WHEEL
datasette_statistics-0.2.1.dist-info/entry_points.txt
datasette_statistics-0.2.1.dist-info/top_level.txt
datasette_statistics-0.2.1.dist-info/RECORD
