Metadata-Version: 2.1
Name: datasette-statistics
Version: 0.2.1
Summary: SQL statistics functions for Datasette
Author: Simon Willison
License: Apache License, Version 2.0
Project-URL: Homepage, https://github.com/simonw/datasette-statistics
Project-URL: Changelog, https://github.com/simonw/datasette-statistics/releases
Project-URL: Issues, https://github.com/simonw/datasette-statistics/issues
Project-URL: CI, https://github.com/simonw/datasette-statistics/actions
Requires-Python: >=3.6
Requires-Dist: datasette
Provides-Extra: test
Requires-Dist: pytest ; extra == 'test'
Requires-Dist: pytest-asyncio ; extra == 'test'
Requires-Dist: pytest-mock ; extra == 'test'
Requires-Dist: sqlite-utils ; extra == 'test'
